{
  "cookies": [
    {
      "name": "session-username",
      "value": "standard_user",
      "domain": "www.saucedemo.com",
      "path": "/",
      "expires": 1776761089,
      "httpOnly": false,
      "secure": false,
      "sameSite": "Lax"
    }
  ],
  "origins": [
    {
      "origin": "https://www.saucedemo.com",
      "localStorage": [
        {
          "name": "backtrace-guid",
          "value": "5a200edf-28ee-4dc0-972b-7aeafe230ea9"
        },
        {
          "name": "backtrace-last-active",
          "value": "1776760489430"
        }
      ]
    }
  ]
}